{"Exif":{"Lat":0,"Long":0,"Date":"2020-10-03T11:52:03+05:30","Tags":{"ApertureValue":4.999999671145473,"Artist":"Aarushi Mahesh","Copyright":"Aarushi Mahesh","CreateDate":"2020:10:03 11:52:03","CustomRendered|uint16":"0","DateTimeOriginal":"2020:10:03 11:52:03","DigitalZoomRatio|*imagemeta.rat[uint32]":"1","ExposureCompensation|*imagemeta.rat[int32]":"1","ExposureTime|*imagemeta.rat[uint32]":"1/13","FNumber|*imagemeta.rat[uint32]":"5","FileSource|uint8":"3","FocalLengthIn35mmFormat|uint16":"112","FocalLength|*imagemeta.rat[uint32]":"75","GainControl|uint16":"0","ISO|uint16":"125","ImageUniqueID":"3d7d4916d48fc43fc4a642f3d28e9aad","LensInfo":"70 300 4.5 6.3","LensModel":"70.0-300.0 mm f/4.5-6.3","LightSource|uint16":"0","Make":"NIKON CORPORATION","MaxApertureValue":4.756828460010884,"Model":"NIKON D5600","ModifyDate":"2021:02:07 19:12:53","OffsetTime":"+05:30","RecommendedExposureIndex|uint32":"125","RelatedImageHeight|uint32":"3791","RelatedImageWidth|uint32":"3004","SceneCaptureType|uint16":"0","SceneType|uint8":"1","SensitivityType|uint16":"2","SerialNumber":"8665661","ShutterSpeedValue":0.07692306189463938,"Software":"Adobe Photoshop Lightroom Classic 9.3 (Windows)","SubSecTimeOriginal|int":"6","SubjectDistanceRange|uint16":"0"}}}
